README.md
setup.py
findCircle/__init__.py
findCircle/findCircle.py
findCircle/test.py
findCircle/test2.py
findCircle.egg-info/PKG-INFO
findCircle.egg-info/SOURCES.txt
findCircle.egg-info/dependency_links.txt
findCircle.egg-info/requires.txt
findCircle.egg-info/top_level.txt
test/test.py